[
  {
    "property_id":"PROP-000010001",
    "title":"Modern studio i centrala Stockholm",
    "description":"Ljus studio nära tunnelbanan",
    "city":"Stockholm",
    "country":"SE",
    "price_per_night":950.00,
    "availability":true
  },
  {
    "property_id":"PROP-000010002",
    "title":"Mysig tvåa vid Avenyn",
    "description":"Nära restauranger och nattliv",
    "city":"Göteborg",
    "country":"SE",
    "price_per_night":890.00,
    "availability":true
  },
  {
    "property_id":"PROP-000010003",
    "title":"Havsutsikt i Västra Hamnen",
    "description":"Balkong med kvällssol",
    "city":"Malmö",
    "country":"SE",
    "price_per_night":1050.00,
    "availability":true
  },
  {
    "property_id":"PROP-000010004",
    "title":"Studentvänlig etta",
    "description":"Tyst område nära uni",
    "city":"Uppsala",
    "country":"SE",
    "price_per_night":650.00,
    "availability":true
  },
  {
    "property_id":"PROP-000010005",
    "title":"Fjällstuga med bastu",
    "description":"Perfekt för vinterhelg",
    "city":"Åre",
    "country":"SE",
    "price_per_night":1400.00,
    "availability":false
  },
  {
    "property_id":"PROP-000010006",
    "title":"Loft i Gamla Stan",
    "description":"Charmigt med synliga bjälkar",
    "city":"Stockholm",
    "country":"SE",
    "price_per_night":1300.00,
    "availability":false
  },
  {
    "property_id":"PROP-000010007",
    "title":"Skärgårdshus på Vaxholm",
    "description":"Egen brygga",
    "city":"Vaxholm",
    "country":"SE",
    "price_per_night":1700.00,
    "availability":true
  },
  {
    "property_id":"PROP-000010008",
    "title":"Nyproducerad trea",
    "description":"Garageplats ingår",
    "city":"Lund",
    "country":"SE",
    "price_per_night":980.00,
    "availability":true
  },
  {
    "property_id":"PROP-000010009",
    "title":"Compact living nära hamnen",
    "description":"Smart planlösning",
    "city":"Helsingborg",
    "country":"SE",
    "price_per_night":720.00,
    "availability":true
  },
  {
    "property_id":"PROP-000010010",
    "title":"Rustik stuga i Dalarna",
    "description":"Öppen spis och natur",
    "city":"Mora",
    "country":"SE",
    "price_per_night":800.00,
    "availability":true
  },
  {
    "property_id":"PROP-000010011",
    "title":"Penthouse med terrass",
    "description":"Utsikt över operan",
    "city":"Oslo",
    "country":"NO",
    "price_per_night":2200.00,
    "availability":false
  },
  {
    "property_id":"PROP-000010012",
    "title":"Hygge-lägenhet på Nørrebro",
    "description":"Café runt hörnet",
    "city":"København",
    "country":"DK",
    "price_per_night":1500.00,
    "availability":true
  },
  {
    "property_id":"PROP-000010013",
    "title":"Designflat i Kallio",
    "description":"Nära metro",
    "city":"Helsinki",
    "country":"FI",
    "price_per_night":1200.00,
    "availability":true
  },
  {
    "property_id":"PROP-000010014",
    "title":"Altbau i Prenzlauer Berg",
    "description":"Högt i tak, trägolv",
    "city":"Berlin",
    "country":"DE",
    "price_per_night":1100.00,
    "availability":true
  },
  {
    "property_id":"PROP-000010015",
    "title":"Strandnära i Barceloneta",
    "description":"2 min till stranden",
    "city":"Barcelona",
    "country":"ES",
    "price_per_night":1350.00,
    "availability":true
  },
  {
    "property_id":"PROP-000010016",
    "title":"Trastevere charm",
    "description":"Genuint kvarter",
    "city":"Roma",
    "country":"IT",
    "price_per_night":1250.00,
    "availability":false
  },
  {
    "property_id":"PROP-000010017",
    "title":"Marais pied-à-terre",
    "description":"Ljus innergård",
    "city":"Paris",
    "country":"FR",
    "price_per_night":1900.00,
    "availability":true
  },
  {
    "property_id":"PROP-000010018",
    "title":"Victorian i Shoreditch",
    "description":"Nära Overground",
    "city":"London",
    "country":"GB",
    "price_per_night":2100.00,
    "availability":true
  },
  {
    "property_id":"PROP-000010019",
    "title":"SoMa micro-loft",
    "description":"Cowork runt hörnet",
    "city":"San Francisco",
    "country":"US",
    "price_per_night":2400.00,
    "availability":false
  },
  {
    "property_id":"PROP-000010020",
    "title":"Brooklyn brownstone room",
    "description":"Trädallé utanför",
    "city":"New York",
    "country":"US",
    "price_per_night":1800.00,
    "availability":true
  },
  {
    "property_id":"PROP-000010021",
    "title":"Ribeira river view",
    "description":"Balkong mot Douro",
    "city":"Porto",
    "country":"PT",
    "price_per_night":900.00,
    "availability":true
  },
  {
    "property_id":"PROP-000010022",
    "title":"Jordaan canal apt",
    "description":"Mysig kanalutsikt",
    "city":"Amsterdam",
    "country":"NL",
    "price_per_night":1600.00,
    "availability":true
  },
  {
    "property_id":"PROP-000010023",
    "title":"Geotermal getaway",
    "description":"Nära Blå Lagunen",
    "city":"Grindavík",
    "country":"IS",
    "price_per_night":1500.00,
    "availability":false
  },
  {
    "property_id":"PROP-000010024",
    "title":"Chalet nära sjö",
    "description":"Perfekt för vandring",
    "city":"Interlaken",
    "country":"CH",
    "price_per_night":2000.00,
    "availability":true
  },
  {
    "property_id":"PROP-000010025",
    "title":"Kaffehus-lägenhet",
    "description":"Spårvagn utanför",
    "city":"Wien",
    "country":"AT",
    "price_per_night":1200.00,
    "availability":true
  },
  {
    "property_id":"PROP-000010026",
    "title":"Plaka studio",
    "description":"Steg från Akropolis",
    "city":"Athina",
    "country":"GR",
    "price_per_night":950.00,
    "availability":true
  },
  {
    "property_id":"PROP-000010027",
    "title":"Dubrovnik old town nest",
    "description":"Historisk charm",
    "city":"Dubrovnik",
    "country":"HR",
    "price_per_night":1150.00,
    "availability":true
  },
  {
    "property_id":"PROP-000010028",
    "title":"Karlín loft",
    "description":"Tyst innergård",
    "city":"Praha",
    "country":"CZ",
    "price_per_night":1000.00,
    "availability":true
  },
  {
    "property_id":"PROP-000010029",
    "title":"Kazimierz nook",
    "description":"Kreativt område",
    "city":"Kraków",
    "country":"PL",
    "price_per_night":850.00,
    "availability":true
  },
  {
    "property_id":"PROP-000010030",
    "title":"Baltic sea view",
    "description":"Högst upp i huset",
    "city":"Tallinn",
    "country":"EE",
    "price_per_night":800.00,
    "availability":true
  }
]
